asyncql/__init__.py
asyncql/exceptions.py
asyncql/py.typed
asyncql/backends/__init__.py
asyncql/backends/mysql.py
asyncql/backends/models/__init__.py
asyncql/backends/models/connection.py
asyncql/backends/models/database.py
asyncql/backends/models/transaction.py
asyncql/common/__init__.py
asyncql/common/imports.py
asyncql/common/query.py
asyncql/models/__init__.py
asyncql/models/connection.py
asyncql/models/database.py
asyncql/models/transaction.py
asyncql/models/url.py
asyncql-0.2.2.dist-info/LICENSE
asyncql-0.2.2.dist-info/METADATA
asyncql-0.2.2.dist-info/WHEEL
asyncql-0.2.2.dist-info/top_level.txt
asyncql-0.2.2.dist-info/RECORD
