Metadata-Version: 2.1
Name: asyncql
Version: 0.2.2
Summary: An asynchronous python library for all your database needs.
Home-page: https://github.com/tsunyoku/asyncql
Author: tsunyoku
Author-email: tsunyoku@gmail.com
License: MIT
Classifier: Development Status :: 2 - Pre-Alpha
Classifier: Environment :: Web Environment
Classifier: Intended Audience :: Developers
Classifier: License :: OSI Approved :: MIT License
Classifier: Operating System :: OS Independent
Classifier: Topic :: Internet :: WWW/HTTP
Classifier: Programming Language :: Python :: 3
Classifier: Programming Language :: Python :: 3.7
Classifier: Programming Language :: Python :: 3.8
Classifier: Programming Language :: Python :: 3.9
Classifier: Programming Language :: Python :: 3.10
Classifier: Programming Language :: Python :: 3 :: Only
Requires-Python: >=3.7
License-File: LICENSE
Provides-Extra: mysql
Requires-Dist: aiomysql ; extra == 'mysql'
Provides-Extra: postgresql
Requires-Dist: asyncpg ; extra == 'postgresql'
Provides-Extra: sqlite
Requires-Dist: aiosqlite ; extra == 'sqlite'
